Workbook

Sheet Inputs
A1: ☕🍦 ICE CREAM & CAFÉ – P&L SIMULATOR
A2: Blue cells = your inputs. All calculations are formulas — change any number and everything updates.
A4: BUSINESS SETTINGS
B5: Business Name | C5: My Store
B6: Target Net Margin % | C6: 0.15
B7: Daily Operating Hours | C7: 10
B8: Days Open per Year | C8: 360
A10: PRODUCT PRICE & COST TABLE
B11: Category | C11: Item | D11: Old Price | E11: New Price | F11: Cost per Unit | G11: Old COGS % | H11: New COGS % | I11: Old Margin $ | J11: New Margin $ | K11: Margin Change
A12: 1 | B12: Icecream | C12: Icecream Kids | D12: 4.5 | E12: 4.25 | F12: 1.2 | G12: =IFERROR(F12/D12,0) -> 0.26666667 | H12: =IFERROR(F12/E12,0) -> 0.28235294 | I12: =D12-F12 -> 3.3 | J12: =E12-F12 -> 3.05 | K12: =J12-I12 -> -0.25
A13: 2 | B13: Icecream | C13: Icecream Medium | D13: 6.25 | E13: 4.95 | F13: 1.4 | G13: =IFERROR(F13/D13,0) -> 0.224 | H13: =IFERROR(F13/E13,0) -> 0.28282828 | I13: =D13-F13 -> 4.85 | J13: =E13-F13 -> 3.55 | K13: =J13-I13 -> -1.3
A14: 3 | B14: Icecream | C14: Icecream Large | D14: 6.25 | E14: 6.95 | F14: 2.1 | G14: =IFERROR(F14/D14,0) -> 0.336 | H14: =IFERROR(F14/E14,0) -> 0.30215827 | I14: =D14-F14 -> 4.15 | J14: =E14-F14 -> 4.85 | K14: =J14-I14 -> 0.7
A15: 4 | B15: Icecream | C15: Hand Packed | D15: 11.45 | E15: 13.95 | F15: 4 | G15: =IFERROR(F15/D15,0) -> 0.34934498 | H15: =IFERROR(F15/E15,0) -> 0.28673835 | I15: =D15-F15 -> 7.45 | J15: =E15-F15 -> 9.95 | K15: =J15-I15 -> 2.5
A16: 5 | B16: Icecream | C16: Sampler | D16: 9.25 | E16: 10.45 | F16: 3 | G16: =IFERROR(F16/D16,0) -> 0.32432432 | H16: =IFERROR(F16/E16,0) -> 0.28708134 | I16: =D16-F16 -> 6.25 | J16: =E16-F16 -> 7.45 | K16: =J16-I16 -> 1.2
A17: 6 | B17: Drinks | C17: Drinks | D17: 6.25 | E17: 6.25 | F17: 0.67 | G17: =IFERROR(F17/D17,0) -> 0.1072 | H17: =IFERROR(F17/E17,0) -> 0.1072 | I17: =D17-F17 -> 5.58 | J17: =E17-F17 -> 5.58 | K17: =J17-I17 -> 0
A18: 7 | B18: Cofee | C18: Coffee - Basic (Americano) | D18: 3.25 | E18: 3.75 | F18: 0.94 | G18: =IFERROR(F18/D18,0) -> 0.28923077 | H18: =IFERROR(F18/E18,0) -> 0.25066667 | I18: =D18-F18 -> 2.31 | J18: =E18-F18 -> 2.81 | K18: =J18-I18 -> 0.5
A19: 8 | B19: Cofee | C19: Coffee - Espresso | D19: 2.75 | E19: 3.25 | F19: 0.94 | G19: =IFERROR(F19/D19,0) -> 0.34181818 | H19: =IFERROR(F19/E19,0) -> 0.28923077 | I19: =D19-F19 -> 1.81 | J19: =E19-F19 -> 2.31 | K19: =J19-I19 -> 0.5
A20: 9 | B20: Cofee | C20: Coffee No Syrup - Cappuccino/Latte | D20: 3.75 | E20: 4.75 | F20: 1.31 | G20: =IFERROR(F20/D20,0) -> 0.34933333 | H20: =IFERROR(F20/E20,0) -> 0.27578947 | I20: =D20-F20 -> 2.44 | J20: =E20-F20 -> 3.44 | K20: =J20-I20 -> 1
A21: 10 | B21: Cofee | C21: Coffee - Mocha | D21: 4.25 | E21: 5.45 | F21: 1.59 | G21: =IFERROR(F21/D21,0) -> 0.37411765 | H21: =IFERROR(F21/E21,0) -> 0.29174312 | I21: =D21-F21 -> 2.66 | J21: =E21-F21 -> 3.86 | K21: =J21-I21 -> 1.2
A22: 11 | B22: Cofee | C22: Spl Coffee | D22: 5.95 | E22: 6.25 | F22: 1.84 | G22: =IFERROR(F22/D22,0) -> 0.3092437 | H22: =IFERROR(F22/E22,0) -> 0.2944 | I22: =D22-F22 -> 4.11 | J22: =E22-F22 -> 4.41 | K22: =J22-I22 -> 0.3
A23: AVERAGES | D23: =AVERAGE(D12:D22) -> 5.8090909 | E23: =AVERAGE(E12:E22) -> 6.3863636 | F23: =AVERAGE(F12:F22) -> 1.7263636 | G23: =AVERAGE(G12:G22) -> 0.29738905 | H23: =AVERAGE(H12:H22) -> 0.26819902 | I23: =AVERAGE(I12:I22) -> 4.0827273 | J23: =AVERAGE(J12:J22) -> 4.66 | K23: =AVERAGE(K12:K22) -> 0.57727273
A25: OPERATING EXPENSES – INDUSTRY BENCHMARKS (Café + Ice Cream Shop)
B26: Expense Category | C26: Monthly ($) | D26: Annual ($) | E26: % of Revenue (benchmark) | F26: Notes
B27: Staffing & Wages | C27: 8500 | D27: =C27*12 -> 102000 | E27: 30–35% of revenue – largest cost for cafés
B28: Rent & Occupancy | C28: 3500 | D28: =C28*12 -> 42000 | E28: 10–15% of revenue – location dependent
B29: Utilities (power/water) | C29: 800 | D29: =C29*12 -> 9600 | E29: 3–5% – refrigeration heavy for ice cream
B30: Supplies & Packaging | C30: 600 | D30: =C30*12 -> 7200 | E30: 2–3% – cups, cones, lids, napkins
B31: Marketing & Promotions | C31: 500 | D31: =C31*12 -> 6000 | E31: 2–4% – social media, local ads
B32: Equipment Maintenance | C32: 300 | D32: =C32*12 -> 3600 | E32: 1–2% – ice cream machines, espresso
B33: Insurance | C33: 250 | D33: =C33*12 -> 3000 | E33: 1% – food business liability
B34: POS / Software / Misc | C34: 200 | D34: =C34*12 -> 2400 | E34: 0.5–1%
B35: TOTAL MONTHLY OPEX | C35: =SUM(C27:C34) -> 14650 | D35: =SUM(D27:D34) -> 175800
A37: COLOUR LEGEND
A38: Blue text = Input (change these)
A39: Pink rows = Icecream category
A40: Blue rows = Drinks category
A41: Green rows = Coffee category

Sheet Sales Mix Simulator
A1: 📊 SALES MIX & VOLUME SIMULATOR
A2: Adjust units sold per item. See how sales mix changes category contribution and overall profit.
A4: UNIT SALES INPUT — Enter how many units sold per day per item
B5: Item | C5: Category | D5: Units/Day | E5: Annual Units | F5: Old Revenue | G5: New Revenue | H5: Old GP $ | I5: New GP $ | J5: Old GP % | K5: New GP %
A6: 1 | B6: Icecream Kids | C6: Icecream | D6: 40 | E6: =D6*Inputs!$C$8 -> 14400 | F6: =E6*Inputs!D12 -> 64800 | G6: =E6*Inputs!E12 -> 61200 | H6: =E6*(Inputs!D12-Inputs!F12) -> 47520 | I6: =E6*(Inputs!E12-Inputs!F12) -> 43920 | J6: =IFERROR(H6/F6,0) -> 0.73333333 | K6: =IFERROR(I6/G6,0) -> 0.71764706
A7: 2 | B7: Icecream Medium | C7: Icecream | D7: 40 | E7: =D7*Inputs!$C$8 -> 14400 | F7: =E7*Inputs!D13 -> 90000 | G7: =E7*Inputs!E13 -> 71280 | H7: =E7*(Inputs!D13-Inputs!F13) -> 69840 | I7: =E7*(Inputs!E13-Inputs!F13) -> 51120 | J7: =IFERROR(H7/F7,0) -> 0.776 | K7: =IFERROR(I7/G7,0) -> 0.71717172
A8: 3 | B8: Icecream Large | C8: Icecream | D8: 20 | E8: =D8*Inputs!$C$8 -> 7200 | F8: =E8*Inputs!D14 -> 45000 | G8: =E8*Inputs!E14 -> 50040 | H8: =E8*(Inputs!D14-Inputs!F14) -> 29880 | I8: =E8*(Inputs!E14-Inputs!F14) -> 34920 | J8: =IFERROR(H8/F8,0) -> 0.664 | K8: =IFERROR(I8/G8,0) -> 0.69784173
A9: 4 | B9: Hand Packed | C9: Icecream | D9: 10 | E9: =D9*Inputs!$C$8 -> 3600 | F9: =E9*Inputs!D15 -> 41220 | G9: =E9*Inputs!E15 -> 50220 | H9: =E9*(Inputs!D15-Inputs!F15) -> 26820 | I9: =E9*(Inputs!E15-Inputs!F15) -> 35820 | J9: =IFERROR(H9/F9,0) -> 0.65065502 | K9: =IFERROR(I9/G9,0) -> 0.71326165
A10: 5 | B10: Sampler | C10: Icecream | D10: 10 | E10: =D10*Inputs!$C$8 -> 3600 | F10: =E10*Inputs!D16 -> 33300 | G10: =E10*Inputs!E16 -> 37620 | H10: =E10*(Inputs!D16-Inputs!F16) -> 22500 | I10: =E10*(Inputs!E16-Inputs!F16) -> 26820 | J10: =IFERROR(H10/F10,0) -> 0.67567568 | K10: =IFERROR(I10/G10,0) -> 0.71291866
A11: 6 | B11: Drinks | C11: Drinks | D11: 30 | E11: =D11*Inputs!$C$8 -> 10800 | F11: =E11*Inputs!D17 -> 67500 | G11: =E11*Inputs!E17 -> 67500 | H11: =E11*(Inputs!D17-Inputs!F17) -> 60264 | I11: =E11*(Inputs!E17-Inputs!F17) -> 60264 | J11: =IFERROR(H11/F11,0) -> 0.8928 | K11: =IFERROR(I11/G11,0) -> 0.8928
A12: 7 | B12: Coffee - Basic (Americano) | C12: Cofee | D12: 0 | E12: =D12*Inputs!$C$8 -> 0 | F12: =E12*Inputs!D18 -> 0 | G12: =E12*Inputs!E18 -> 0 | H12: =E12*(Inputs!D18-Inputs!F18) -> 0 | I12: =E12*(Inputs!E18-Inputs!F18) -> 0 | J12: =IFERROR(H12/F12,0) -> 0 | K12: =IFERROR(I12/G12,0) -> 0
A13: 8 | B13: Coffee - Espresso | C13: Cofee | D13: 0 | E13: =D13*Inputs!$C$8 -> 0 | F13: =E13*Inputs!D19 -> 0 | G13: =E13*Inputs!E19 -> 0 | H13: =E13*(Inputs!D19-Inputs!F19) -> 0 | I13: =E13*(Inputs!E19-Inputs!F19) -> 0 | J13: =IFERROR(H13/F13,0) -> 0 | K13: =IFERROR(I13/G13,0) -> 0
A14: 9 | B14: Coffee No Syrup - Cappuccino/Latte | C14: Cofee | D14: 5 | E14: =D14*Inputs!$C$8 -> 1800 | F14: =E14*Inputs!D20 -> 6750 | G14: =E14*Inputs!E20 -> 8550 | H14: =E14*(Inputs!D20-Inputs!F20) -> 4392 | I14: =E14*(Inputs!E20-Inputs!F20) -> 6192 | J14: =IFERROR(H14/F14,0) -> 0.65066667 | K14: =IFERROR(I14/G14,0) -> 0.72421053
A15: 10 | B15: Coffee - Mocha | C15: Cofee | D15: 5 | E15: =D15*Inputs!$C$8 -> 1800 | F15: =E15*Inputs!D21 -> 7650 | G15: =E15*Inputs!E21 -> 9810 | H15: =E15*(Inputs!D21-Inputs!F21) -> 4788 | I15: =E15*(Inputs!E21-Inputs!F21) -> 6948 | J15: =IFERROR(H15/F15,0) -> 0.62588235 | K15: =IFERROR(I15/G15,0) -> 0.70825688
A16: 11 | B16: Spl Coffee | C16: Cofee | D16: 25 | E16: =D16*Inputs!$C$8 -> 9000 | F16: =E16*Inputs!D22 -> 53550 | G16: =E16*Inputs!E22 -> 56250 | H16: =E16*(Inputs!D22-Inputs!F22) -> 36990 | I16: =E16*(Inputs!E22-Inputs!F22) -> 39690 | J16: =IFERROR(H16/F16,0) -> 0.6907563 | K16: =IFERROR(I16/G16,0) -> 0.7056
A17: TOTAL ALL ITEMS | D17: =SUM(D6:D16) -> 185 | E17: =SUM(E6:E16) -> 66600 | F17: =SUM(F6:F16) -> 409770 | G17: =SUM(G6:G16) -> 412470 | H17: =SUM(H6:H16) -> 302994 | I17: =SUM(I6:I16) -> 305694 | J17: =IFERROR(H17/F17,0) -> 0.73942456 | K17: =IFERROR(I17/G17,0) -> 0.74113026
A19: CATEGORY CONTRIBUTION ANALYSIS
B20: Category | C20: Units/Day | D20: Annual Units | E20: Revenue Mix % | F20: Old Revenue | G20: New Revenue | H20: Old Gross Profit | I20: New Gross Profit | J20: Old GP % | K20: New GP %
B21: Icecream | C21: =SUM(D6,D7,D8,D9,D10) -> 120 | D21: =SUM(E6,E7,E8,E9,E10) -> 43200 | E21: =IFERROR(G21/G17,0) -> 0.65546585 | F21: =SUM(F6,F7,F8,F9,F10) -> 274320 | G21: =SUM(G6,G7,G8,G9,G10) -> 270360 | H21: =SUM(H6,H7,H8,H9,H10) -> 196560 | I21: =SUM(I6,I7,I8,I9,I10) -> 192600 | J21: =IFERROR(H21/F21,0) -> 0.71653543 | K21: =IFERROR(I21/G21,0) -> 0.71238349
B22: Drinks | C22: =SUM(D11) -> 30 | D22: =SUM(E11) -> 10800 | E22: =IFERROR(G22/G17,0) -> 0.16364827 | F22: =SUM(F11) -> 67500 | G22: =SUM(G11) -> 67500 | H22: =SUM(H11) -> 60264 | I22: =SUM(I11) -> 60264 | J22: =IFERROR(H22/F22,0) -> 0.8928 | K22: =IFERROR(I22/G22,0) -> 0.8928
B23: Cofee | C23: =SUM(D12,D13,D14,D15,D16) -> 35 | D23: =SUM(E12,E13,E14,E15,E16) -> 12600 | E23: =IFERROR(G23/G17,0) -> 0.18088588 | F23: =SUM(F12,F13,F14,F15,F16) -> 67950 | G23: =SUM(G12,G13,G14,G15,G16) -> 74610 | H23: =SUM(H12,H13,H14,H15,H16) -> 46170 | I23: =SUM(I12,I13,I14,I15,I16) -> 52830 | J23: =IFERROR(H23/F23,0) -> 0.6794702 | K23: =IFERROR(I23/G23,0) -> 0.70808203

Sheet P&L Analysis
A1: 📈 P&L ANALYSIS – OLD RATES vs NEW RATES
A2: Full P&L comparing old vs new pricing, with OPEX and margin guidance.
A4: P&L Line Item | B4: OLD Rates ($) | C4: OLD Rates (%) | E4: NEW Rates ($) | F4: NEW Rates (%) | G4: Difference
A5: REVENUE
A6: Icecream Revenue | B6: ='Sales Mix Simulator'!F21 -> 274320 | C6: =IFERROR(B6/'Sales Mix Simulator'!F17,0) -> 0.66944872 | E6: ='Sales Mix Simulator'!G21 -> 270360 | F6: =IFERROR(E6/'Sales Mix Simulator'!G17,0) -> 0.65546585 | G6: =E6-B6 -> -3960
A7: Drinks Revenue | B7: ='Sales Mix Simulator'!F22 -> 67500 | C7: =IFERROR(B7/'Sales Mix Simulator'!F17,0) -> 0.16472655 | E7: ='Sales Mix Simulator'!G22 -> 67500 | F7: =IFERROR(E7/'Sales Mix Simulator'!G17,0) -> 0.16364827 | G7: =E7-B7 -> 0
A8: Cofee Revenue | B8: ='Sales Mix Simulator'!F23 -> 67950 | C8: =IFERROR(B8/'Sales Mix Simulator'!F17,0) -> 0.16582473 | E8: ='Sales Mix Simulator'!G23 -> 74610 | F8: =IFERROR(E8/'Sales Mix Simulator'!G17,0) -> 0.18088588 | G8: =E8-B8 -> 6660
A9: TOTAL REVENUE | B9: ='Sales Mix Simulator'!F17 -> 409770 | C9: =IFERROR(B9/B9,0) -> 1 | E9: ='Sales Mix Simulator'!G17 -> 412470 | F9: =IFERROR(E9/E9,0) -> 1 | G9: =E9-B9 -> 2700
A11: COST OF GOODS SOLD (COGS)
A12: Icecream COGS | B12: ='Sales Mix Simulator'!F21-'Sales Mix Simulator'!H21 -> 77760 | C12: =IFERROR(B12/B9,0) -> 0.18976499 | E12: ='Sales Mix Simulator'!G21-'Sales Mix Simulator'!I21 -> 77760 | F12: =IFERROR(E12/E9,0) -> 0.1885228 | G12: =E12-B12 -> 0
A13: Drinks COGS | B13: ='Sales Mix Simulator'!F22-'Sales Mix Simulator'!H22 -> 7236 | C13: =IFERROR(B13/B9,0) -> 0.017658687 | E13: ='Sales Mix Simulator'!G22-'Sales Mix Simulator'!I22 -> 7236 | F13: =IFERROR(E13/E9,0) -> 0.017543094 | G13: =E13-B13 -> 0
A14: Cofee COGS | B14: ='Sales Mix Simulator'!F23-'Sales Mix Simulator'!H23 -> 21780 | C14: =IFERROR(B14/B9,0) -> 0.053151768 | E14: ='Sales Mix Simulator'!G23-'Sales Mix Simulator'!I23 -> 21780 | F14: =IFERROR(E14/E9,0) -> 0.05280384 | G14: =E14-B14 -> 0
A15: TOTAL COGS | B15: =B12+B13+B14 -> 106776 | C15: =IFERROR(B15/B9,0) -> 0.26057544 | E15: =E12+E13+E14 -> 106776 | F15: =IFERROR(E15/E9,0) -> 0.25886974 | G15: =E15-B15 -> 0
A16: GROSS PROFIT | B16: =B9-B15 -> 302994 | C16: =IFERROR(B16/B9,0) -> 0.73942456 | E16: =E9-E15 -> 305694 | F16: =IFERROR(E16/E9,0) -> 0.74113026 | G16: =E16-B16 -> 2700
A18: OPERATING EXPENSES (OPEX)
A19: Staffing & Wages | B19: =Inputs!D27 -> 102000 | C19: =IFERROR(B19/B9,0) -> 0.24892013 | E19: =Inputs!D27 -> 102000 | F19: =IFERROR(E19/E9,0) -> 0.24729071 | G19: =0 -> 0
A20: Rent & Occupancy | B20: =Inputs!D28 -> 42000 | C20: =IFERROR(B20/B9,0) -> 0.10249652 | E20: =Inputs!D28 -> 42000 | F20: =IFERROR(E20/E9,0) -> 0.10182559 | G20: =0 -> 0
A21: Utilities (power/water) | B21: =Inputs!D29 -> 9600 | C21: =IFERROR(B21/B9,0) -> 0.023427777 | E21: =Inputs!D29 -> 9600 | F21: =IFERROR(E21/E9,0) -> 0.02327442 | G21: =0 -> 0
A22: Supplies & Packaging | B22: =Inputs!D30 -> 7200 | C22: =IFERROR(B22/B9,0) -> 0.017570832 | E22: =Inputs!D30 -> 7200 | F22: =IFERROR(E22/E9,0) -> 0.017455815 | G22: =0 -> 0
A23: Marketing & Promotions | B23: =Inputs!D31 -> 6000 | C23: =IFERROR(B23/B9,0) -> 0.01464236 | E23: =Inputs!D31 -> 6000 | F23: =IFERROR(E23/E9,0) -> 0.014546512 | G23: =0 -> 0
A24: Equipment Maintenance | B24: =Inputs!D32 -> 3600 | C24: =IFERROR(B24/B9,0) -> 0.0087854162 | E24: =Inputs!D32 -> 3600 | F24: =IFERROR(E24/E9,0) -> 0.0087279075 | G24: =0 -> 0
A25: Insurance | B25: =Inputs!D33 -> 3000 | C25: =IFERROR(B25/B9,0) -> 0.0073211802 | E25: =Inputs!D33 -> 3000 | F25: =IFERROR(E25/E9,0) -> 0.0072732562 | G25: =0 -> 0
A26: POS / Software / Misc | B26: =Inputs!D34 -> 2400 | C26: =IFERROR(B26/B9,0) -> 0.0058569441 | E26: =Inputs!D34 -> 2400 | F26: =IFERROR(E26/E9,0) -> 0.005818605 | G26: =0 -> 0
A27: TOTAL OPEX | B27: =Inputs!D35 -> 175800 | C27: =IFERROR(B27/B9,0) -> 0.42902116 | E27: =Inputs!D35 -> 175800 | F27: =IFERROR(E27/E9,0) -> 0.42621282 | G27: =E27-B27 -> 0
A29: EBITDA (Earnings Before Tax) | B29: =B16-B27 -> 127194 | C29: =IFERROR(B29/B9,0) -> 0.3104034 | E29: =E16-E27 -> 129894 | F29: =IFERROR(E29/E9,0) -> 0.31491745 | G29: =E29-B29 -> 2700
A30: Tax Rate (input below) | B30: 0.08
A31: NET INCOME (After Tax) | B31: =B29*(1-B30) -> 117018.48 | C31: =IFERROR(B31/B9,0) -> 0.28557113 | E31: =E29*(1-B30) -> 119502.48 | F31: =IFERROR(E31/E9,0) -> 0.28972405 | G31: =E31-B31 -> 2484
A33: 🎯 MARGIN GUIDANCE – CAN YOU HIT YOUR TARGET?
A34: Target Net Margin % | B34: =Inputs!C6 -> 0.15
A35: Actual Net Margin (Old Rates) | B35: =IFERROR(B31/B9,0) -> 0.28557113
A36: Actual Net Margin (New Rates) | B36: =IFERROR(E31/E9,0) -> 0.28972405
A37: Gap – Old Rates vs Target | B37: =B35-B34 -> 0.13557113
A38: Gap – New Rates vs Target | B38: =B36-B34 -> 0.13972405
A39: Revenue needed (Old) to hit target | B39: =IFERROR((Inputs!D35+B15)/(1-Inputs!C5-IFERROR(B15/B9,0.3)),0) -> 0
A40: Revenue needed (New) to hit target | B40: =IFERROR((Inputs!D35+E15)/(1-Inputs!C5-IFERROR(E15/E9,0.3)),0) -> 0

Sheet Mix Impact Analysis
A1: 🔀 SALES MIX IMPACT – WHAT HAPPENS IF YOU SELL MORE OF ONE CATEGORY?
A2: See what profit you make at different sales mixes. E.g. if 90% of sales is Ice Cream, can you still hit your margin target?
A4: CATEGORY MIX SCENARIO BUILDER
A5: Total Daily Units (all categories) | B5: 190
A6: Enter the sales MIX % per category below (must add to 100%):
A7: Icecream — % of total sales | B7: 0.4 | C7: =ROUND(B5*B7,0) -> 76 | D7: Units/Day →
A8: Drinks — % of total sales | B8: 0.3 | C8: =ROUND(B5*B8,0) -> 57 | D8: Units/Day →
A9: Cofee — % of total sales | B9: 0.3 | C9: =ROUND(B5*B9,0) -> 57 | D9: Units/Day →
A10: Total Mix % (must = 100%) | B10: =B7+B8+B9 -> 1 | C10: =IF(ABS(B10-1)<0.001,"✅ OK","⚠️ Fix mix!") -> ✅ OK
A12: SCENARIO RESULTS — NEW RATES
A13: Category | B13: Units/Day | C13: Annual Units | D13: Revenue | E13: COGS | F13: Gross Profit | G13: GP % | H13: Contribution to Total GP | I13: Mix % of Revenue
A14: Icecream | B14: =C7 -> 76 | C14: =C7*Inputs!D7 -> 0 | D14: =C14*AVERAGE(Inputs!E12,Inputs!E13,Inputs!E14,Inputs!E15,Inputs!E16) -> 0 | E14: =C14*AVERAGE(Inputs!F12,Inputs!F13,Inputs!F14,Inputs!F15,Inputs!F16) -> 0 | F14: =D14-E14 -> 0 | G14: =IFERROR(F14/D14,0) -> 0 | H14: =IFERROR(F14/F17,0) -> 0 | I14: =IFERROR(D14/D17,0) -> 0
A15: Drinks | B15: =C8 -> 57 | C15: =C8*Inputs!D7 -> 0 | D15: =C15*AVERAGE(Inputs!E17) -> 0 | E15: =C15*AVERAGE(Inputs!F17) -> 0 | F15: =D15-E15 -> 0 | G15: =IFERROR(F15/D15,0) -> 0 | H15: =IFERROR(F15/F17,0) -> 0 | I15: =IFERROR(D15/D17,0) -> 0
A16: Cofee | B16: =C9 -> 57 | C16: =C9*Inputs!D7 -> 0 | D16: =C16*AVERAGE(Inputs!E18,Inputs!E19,Inputs!E20,Inputs!E21,Inputs!E22) -> 0 | E16: =C16*AVERAGE(Inputs!F18,Inputs!F19,Inputs!F20,Inputs!F21,Inputs!F22) -> 0 | F16: =D16-E16 -> 0 | G16: =IFERROR(F16/D16,0) -> 0 | H16: =IFERROR(F16/F17,0) -> 0 | I16: =IFERROR(D16/D17,0) -> 0
A17: TOTAL | B17: =SUM(B14,B15,B16) -> 190 | C17: =SUM(C14,C15,C16) -> 0 | D17: =SUM(D14,D15,D16) -> 0 | E17: =SUM(E14,E15,E16) -> 0 | F17: =SUM(F14,F15,F16) -> 0 | G17: =IFERROR(F17/D17,0) -> 0 | H17: 100.0% | I17: 100.0%
A19: 🎯 CAN THIS MIX HIT YOUR MARGIN TARGET?
A20: Gross Profit (this mix) | B20: =F17 -> 0
A21: Annual OPEX | B21: =Inputs!D35 -> 175800
A22: EBITDA | B22: =B20-B21 -> -175800
A23: Revenue | B23: =D17 -> 0
A24: Net Income (est. 25% tax) | B24: =B22*0.75 -> -131850
A25: Actual Net Margin % | B25: =IFERROR(B24/B23,0) -> 0
A26: Target Net Margin % | B26: =Inputs!C6 -> 0.15
A27: Gap to Target | B27: =B25-B26 -> -0.15
A28: Verdict | B28: =IF(B25>=B26,"✅ YES — this mix hits your target!","⚠️ NO — "&TEXT(ABS(B27),"0.0%")&" short. Push Coffee & Drinks more.") -> ⚠️ NO — 15.0% short. Push Coffee & Drinks more.

Sheet Marketing Guidance
A1: 📣 MARKETING GUIDANCE – WHICH PRODUCTS TO PUSH?
A2: Products ranked by new gross margin. Higher margin = push harder. Use this to guide promos & staff upselling.
A4: PRODUCT RANKING BY GROSS MARGIN % (New Rates)
A5: Item | B5: Category | C5: New Price | D5: Gross Margin $ | E5: Gross Margin %
A6: Drinks | B6: Drinks | C6: =Inputs!E17 -> 6.25 | D6: =Inputs!E17-Inputs!F17 -> 5.58 | E6: =IFERROR((Inputs!E17-Inputs!F17)/Inputs!E17,0) -> 0.8928
A7: Coffee - Basic (Americano) | B7: Cofee | C7: =Inputs!E18 -> 3.75 | D7: =Inputs!E18-Inputs!F18 -> 2.81 | E7: =IFERROR((Inputs!E18-Inputs!F18)/Inputs!E18,0) -> 0.74933333
A8: Coffee No Syrup - Cappuccino/Latte | B8: Cofee | C8: =Inputs!E20 -> 4.75 | D8: =Inputs!E20-Inputs!F20 -> 3.44 | E8: =IFERROR((Inputs!E20-Inputs!F20)/Inputs!E20,0) -> 0.72421053
A9: Icecream Kids | B9: Icecream | C9: =Inputs!E12 -> 4.25 | D9: =Inputs!E12-Inputs!F12 -> 3.05 | E9: =IFERROR((Inputs!E12-Inputs!F12)/Inputs!E12,0) -> 0.71764706
A10: Icecream Medium | B10: Icecream | C10: =Inputs!E13 -> 4.95 | D10: =Inputs!E13-Inputs!F13 -> 3.55 | E10: =IFERROR((Inputs!E13-Inputs!F13)/Inputs!E13,0) -> 0.71717172
A11: Hand Packed | B11: Icecream | C11: =Inputs!E15 -> 13.95 | D11: =Inputs!E15-Inputs!F15 -> 9.95 | E11: =IFERROR((Inputs!E15-Inputs!F15)/Inputs!E15,0) -> 0.71326165
A12: Sampler | B12: Icecream | C12: =Inputs!E16 -> 10.45 | D12: =Inputs!E16-Inputs!F16 -> 7.45 | E12: =IFERROR((Inputs!E16-Inputs!F16)/Inputs!E16,0) -> 0.71291866
A13: Coffee - Espresso | B13: Cofee | C13: =Inputs!E19 -> 3.25 | D13: =Inputs!E19-Inputs!F19 -> 2.31 | E13: =IFERROR((Inputs!E19-Inputs!F19)/Inputs!E19,0) -> 0.71076923
A14: Coffee - Mocha | B14: Cofee | C14: =Inputs!E21 -> 5.45 | D14: =Inputs!E21-Inputs!F21 -> 3.86 | E14: =IFERROR((Inputs!E21-Inputs!F21)/Inputs!E21,0) -> 0.70825688
A15: Spl Coffee | B15: Cofee | C15: =Inputs!E22 -> 6.25 | D15: =Inputs!E22-Inputs!F22 -> 4.41 | E15: =IFERROR((Inputs!E22-Inputs!F22)/Inputs!E22,0) -> 0.7056
A16: Icecream Large | B16: Icecream | C16: =Inputs!E14 -> 6.95 | D16: =Inputs!E14-Inputs!F14 -> 4.85 | E16: =IFERROR((Inputs!E14-Inputs!F14)/Inputs!E14,0) -> 0.69784173
A18: CATEGORY AVERAGE MARGIN — New Rates
A19: Icecream — Average Gross Margin % | B19: =IFERROR(AVERAGE((Inputs!E12-Inputs!F12)/Inputs!E12,(Inputs!E13-Inputs!F13)/Inputs!E13,(Inputs!E14-Inputs!F14)/Inputs!E14,(Inputs!E15-Inputs!F15)/Inputs!E15,(Inputs!E16-Inputs!F16)/Inputs!E16),0) -> 0.71176816
A20: Drinks — Average Gross Margin % | B20: =IFERROR(AVERAGE((Inputs!E17-Inputs!F17)/Inputs!E17),0) -> 0.8928
A21: Cofee — Average Gross Margin % | B21: =IFERROR(AVERAGE((Inputs!E18-Inputs!F18)/Inputs!E18,(Inputs!E19-Inputs!F19)/Inputs!E19,(Inputs!E20-Inputs!F20)/Inputs!E20,(Inputs!E21-Inputs!F21)/Inputs!E21,(Inputs!E22-Inputs!F22)/Inputs!E22),0) -> 0.71963399
A23: 💡 STRATEGIC GUIDANCE
A24: ▶ Push Coffee hard | B24: Coffee items have the highest gross margins (70%+). Every extra coffee sale significantly boosts profit.
A25: ▶ Ice Cream volume is key | B25: IC margins are good but need HIGH volume to cover OPEX. Low IC volume = loss.
A26: ▶ Drinks are your safety net | B26: Drinks have consistent margins. Upsell a drink with every order.
A27: ▶ New rates are better | B27: Most new prices increase margins. Especially Hand Packed & Sampler.
A28: ▶ Avoid 90% IC dependency | B28: If 90% of sales is ice cream, OPEX will likely erode all profit. Aim for 50/25/25 mix.
A29: ▶ Upsell combos | B29: Combo deals (IC + Coffee) improve average transaction value and margin mix.
